fedfred/__about__.py
fedfred/__init__.py
fedfred/clients.py
fedfred/config.py
fedfred/helpers.py
fedfred/objects.py
fedfred/py.typed
fedfred-3.0.0.dist-info/LICENSE
fedfred-3.0.0.dist-info/METADATA
fedfred-3.0.0.dist-info/WHEEL
fedfred-3.0.0.dist-info/RECORD
