Metadata-Version: 2.3
Name: fedfred
Version: 3.0.0
Summary: A feature-rich python package for interacting with the Federal Reserve Bank of St. Louis Economic Database: FRED
License: MIT
Keywords: fred,federal reserve,api,economics,finance,economic data,financial data,fred pandas,fred polars,fred dask,fred geopandas,async,pandas,polars,dask,geopandas,cache,financial analysis,economic analysis,data analysis,data science,data visualization,data mining,data wrangling,data cleaning
Author: Nikhil Sunder
Author-email: nsunder724@gmail.com
Requires-Python: >=3.10,<4.0
Classifier: Development Status :: 5 - Production/Stable
Classifier: Intended Audience :: Financial and Insurance Industry
Classifier: License :: OSI Approved :: MIT License
Classifier: Operating System :: OS Independent
Classifier: Programming Language :: Python :: 3
Classifier: Programming Language :: Python :: 3.10
Classifier: Programming Language :: Python :: 3.11
Classifier: Programming Language :: Python :: 3.12
Classifier: Programming Language :: Python :: 3.13
Classifier: Topic :: Office/Business :: Financial :: Investment
Provides-Extra: dask
Provides-Extra: polars
Provides-Extra: types
Requires-Dist: asyncache
Requires-Dist: cachetools
Requires-Dist: geopandas
Requires-Dist: httpx
Requires-Dist: pandas
Requires-Dist: tenacity
Project-URL: Documentation, https://nikhilxsunder.github.io/fedfred/
Project-URL: Repository, https://github.com/nikhilxsunder/fedfred
